rnaget_client/__init__.py
rnaget_client-0.0.1.dist-info/LICENSE
rnaget_client-0.0.1.dist-info/METADATA
rnaget_client-0.0.1.dist-info/WHEEL
rnaget_client-0.0.1.dist-info/RECORD
