Metadata-Version: 2.1
Name: rnaget-client
Version: 0.0.1
Summary: A python client to query the RNAget compliant servers
Author: Emilio
Author-email: righiemilio@gmail.com
Requires-Python: >=3.10,<4.0
Classifier: Programming Language :: Python :: 3
Classifier: Programming Language :: Python :: 3.10
Classifier: Programming Language :: Python :: 3.11
Requires-Dist: requests (>=2,<3)
